assignment_04/TopEntity.v
module TopEntity(
    input       clk,
	input 	 	btn1,		// as a manual reset line.
    input       PITCH_DIRA,  // Pin assignment for dir[0]
    input       PITCH_DIRB,  // Pin assignment for dir[1]
    output reg  led1,		// clockwise direction indication
    output reg  led2		// counterclockwise direction indication
);

// State of state machine, bits correspond to A and B dir.
parameter S00 = 2'b00;
parameter S01 = 2'b01;
parameter S10 = 2'b10;
parameter S11 = 2'b11;

parameter steps_per_revolution = 1;

// Current and previous state
reg [1:0] current_state = S00;
reg [1:0] previous_state = S00;

// Combine PITCH_DIRA and PITCH_DIRB into a 2-bit vector
wire [1:0] dir;
assign dir = {PITCH_DIRA, PITCH_DIRB};

// Counter for steps and display
reg [7:0] steps = 0; 
reg [7:0] previous_steps = 0;

// Sequential logic: state update and counter/LEDs on clock edge
always @(posedge clk) begin

	if(btn1) begin
		led1 <= 0;
		led2 <= 0;
		current_state <= S00;
		previous_state <= S00;
		steps <= 0;
		previous_steps <= 0;
	end

	// Save previous state for edge detection
	previous_state <= current_state;
	previous_steps <= steps;

	// Compute next state (combinational logic folded into sequential)
	case (current_state)
		S00: begin
			if (dir == S10) begin
				current_state <= S10;
				steps <= steps + 1;
			end else if (dir == S01) begin
				current_state <= S01;
				steps <= steps - 1;
			end else begin
				current_state <= S00;
			end
		end
		S01: begin
			if (dir == S11) begin 
				current_state <= S11;
				steps <= steps + 1;
			end else if (dir == S00) begin
				current_state <= S00;
				steps <= steps - 1;
			end else begin
				current_state <= S01;
			end
		end
		S10: begin
			if (dir == S00) begin
				current_state <= S00;
				steps <= steps - 1;
			end else if (dir == S11) begin
				current_state <= S11;
				steps <= steps + 1;
			end else begin
				current_state <= S10;
			end
		end
		S11: begin
			if (dir == S01) begin
				current_state <= S01;
				steps <= steps + 1;
			end else if (dir == S10) begin
				current_state <= S10;
				steps <= steps - 1;
			end else begin
				current_state <= S11;
			end
		end
		default: current_state <= S00;
	endcase

	// Assign an LED to indicate the direction of rotation.
	if(previous_steps < steps) begin
		// Clockwise
		// led1 <= 1; 
		// led2 <= 0;
	end else if (previous_steps > steps) begin
		// Counterclockwise
		// led1 <= 0;
		// led2 <= 1; 
	end

	if(steps / steps_per_revolution >= 1) begin
		led1 <= 1; // Turn on LED1 for one revolution
		led2 <= 0;
	end else if (steps / steps_per_revolution <= -1) begin
		led1 <= 0;
		led2 <= 1; // Turn on LED2 for one revolution in the opposite direction
	end else begin
		led1 <= 0;
		led2 <= 0; // Both LEDs off when less than one revolution
	end
end
endmodule

assignment_04/TopEntity_tb.v
`include "TopEntity.v" // Include YOUR entity.
`timescale 1ns / 1ps  // Time unit = period, precision
module TopEntity_tb;
  reg clk;
  reg btn1;
  reg PITCH_DIRA;
  reg PITCH_DIRB;
  wire led1;
  wire led2;

  integer i;
  integer j;

  TopEntity dut (
      .clk(clk),
      .btn1(btn1),
      .PITCH_DIRA(PITCH_DIRA),
      .PITCH_DIRB(PITCH_DIRB),
      .led1(led1),
      .led2(led2)
  );

  // Generate clock signal
  initial begin
    clk = 0;
    forever #1 clk = ~clk;
  end

  // Testbench script
  initial begin
    $dumpfile("signals.vcd");  // Name of the signal dump file
    $dumpvars(0, TopEntity_tb);  // Signals to dump

    // Initialize inputs
    btn1 = 0;
    PITCH_DIRA = 0;
    PITCH_DIRB = 0;

    // Reset the system
    btn1 = 1;
    #5;
    btn1 = 0;


 // Simulate CW rotation (Clockwise)
    for (j = 0; j < 10; j = j + 1) begin
      for (i = 0; i < 4; i = i + 1) begin
        case (i)
          0: {PITCH_DIRA, PITCH_DIRB} = 2'b00;
          1: {PITCH_DIRA, PITCH_DIRB} = 2'b10;
          2: {PITCH_DIRA, PITCH_DIRB} = 2'b11;
          3: {PITCH_DIRA, PITCH_DIRB} = 2'b01;
        endcase
        #10;
      end
    end

    // Simulate CCW rotation (Counterclockwise)
    for (j = 0; j < 5; j = j + 1) begin
      for (i = 0; i < 4; i = i + 1) begin
        case (i)
          0: {PITCH_DIRA, PITCH_DIRB} = 2'b00;
          1: {PITCH_DIRA, PITCH_DIRB} = 2'b01;
          2: {PITCH_DIRA, PITCH_DIRB} = 2'b11;
          3: {PITCH_DIRA, PITCH_DIRB} = 2'b10;
        endcase
        #10;
      end
    end

   

    #500; // Allow time for simulation
    $finish;  // End simulation
  end
endmodule

assignment_04/signals.vcd
$date
	Sat May  2 14:46:16 2026
$end
$version
	Icarus Verilog
$end
$timescale
	1ps
$end
$scope module TopEntity_tb $end
$var wire 1 ! led2 $end
$var wire 1 " led1 $end
$var reg 1 # PITCH_DIRA $end
$var reg 1 $ PITCH_DIRB $end
$var reg 1 % btn1 $end
$var reg 1 & clk $end
$var integer 32 ' i [31:0] $end
$var integer 32 ( j [31:0] $end
$scope module dut $end
$var wire 1 # PITCH_DIRA $end
$var wire 1 $ PITCH_DIRB $end
$var wire 1 % btn1 $end
$var wire 1 & clk $end
$var wire 2 ) dir [1:0] $end
$var parameter 2 * S00 $end
$var parameter 2 + S01 $end
$var parameter 2 , S10 $end
$var parameter 2 - S11 $end
$var parameter 32 . steps_per_revolution $end
$var reg 2 / current_state [1:0] $end
$var reg 1 " led1 $end
$var reg 1 ! led2 $end
$var reg 2 0 previous_state [1:0] $end
$var reg 8 1 previous_steps [7:0] $end
$var reg 8 2 steps [7:0] $end
$upscope $end
$upscope $end
$enddefinitions $end
$comment Show the parameter values. $end
$dumpall
b1 .
b11 -
b10 ,
b1 +
b0 *
$end
#0
$dumpvars
b0 2
b0 1
b0 0
b0 /
b0 )
bx (
bx '
0&
1%
0$
0#
x"
x!
$end
#1000
1!
0"
1&
#2000
0&
#3000
1!
1&
#4000
0&
#5000
1&
b0 '
b0 (
0%
#6000
0&
#7000
1&
#8000
0&
#9000
1&
#10000
0&
#11000
1&
#12000
0&
#13000
1&
#14000
0&
#15000
b1 2
b10 /
1&
b10 )
1#
b1 '
#16000
0&
#17000
0!
1"
b1 1
b10 0
1&
#18000
0&
#19000
1&
#20000
0&
#21000
1&
#22000
0&
#23000
1&
#24000
0&
#25000
b10 2
b11 /
1&
b11 )
1$
b10 '
#26000
0&
#27000
b10 1
b11 0
1&
#28000
0&
#29000
1&
#30000
0&
#31000
1&
#32000
0&
#33000
1&
#34000
0&
#35000
b11 2
b1 /
1&
b1 )
0#
b11 '
#36000
0&
#37000
b11 1
b1 0
1&
#38000
0&
#39000
1&
#40000
0&
#41000
1&
#42000
0&
#43000
1&
#44000
0&
#45000
b10 2
b0 /
1&
b0 )
0$
b1 (
b0 '
#46000
0&
#47000
b10 1
b0 0
1&
#48000
0&
#49000
1&
#50000
0&
#51000
1&
#52000
0&
#53000
1&
#54000
0&
#55000
b11 2
b10 /
1&
b10 )
1#
b1 '
#56000
0&
#57000
b11 1
b10 0
1&
#58000
0&
#59000
1&
#60000
0&
#61000
1&
#62000
0&
#63000
1&
#64000
0&
#65000
b100 2
b11 /
1&
b11 )
1$
b10 '
#66000
0&
#67000
b100 1
b11 0
1&
#68000
0&
#69000
1&
#70000
0&
#71000
1&
#72000
0&
#73000
1&
#74000
0&
#75000
b101 2
b1 /
1&
b1 )
0#
b11 '
#76000
0&
#77000
b101 1
b1 0
1&
#78000
0&
#79000
1&
#80000
0&
#81000
1&
#82000
0&
#83000
1&
#84000
0&
#85000
b100 2
b0 /
1&
b0 )
0$
b10 (
b0 '
#86000
0&
#87000
b100 1
b0 0
1&
#88000
0&
#89000
1&
#90000
0&
#91000
1&
#92000
0&
#93000
1&
#94000
0&
#95000
b101 2
b10 /
1&
b10 )
1#
b1 '
#96000
0&
#97000
b101 1
b10 0
1&
#98000
0&
#99000
1&
#100000
0&
#101000
1&
#102000
0&
#103000
1&
#104000
0&
#105000
b110 2
b11 /
1&
b11 )
1$
b10 '
#106000
0&
#107000
b110 1
b11 0
1&
#108000
0&
#109000
1&
#110000
0&
#111000
1&
#112000
0&
#113000
1&
#114000
0&
#115000
b111 2
b1 /
1&
b1 )
0#
b11 '
#116000
0&
#117000
b111 1
b1 0
1&
#118000
0&
#119000
1&
#120000
0&
#121000
1&
#122000
0&
#123000
1&
#124000
0&
#125000
b110 2
b0 /
1&
b0 )
0$
b11 (
b0 '
#126000
0&
#127000
b110 1
b0 0
1&
#128000
0&
#129000
1&
#130000
0&
#131000
1&
#132000
0&
#133000
1&
#134000
0&
#135000
b111 2
b10 /
1&
b10 )
1#
b1 '
#136000
0&
#137000
b111 1
b10 0
1&
#138000
0&
#139000
1&
#140000
0&
#141000
1&
#142000
0&
#143000
1&
#144000
0&
#145000
b1000 2
b11 /
1&
b11 )
1$
b10 '
#146000
0&
#147000
b1000 1
b11 0
1&
#148000
0&
#149000
1&
#150000
0&
#151000
1&
#152000
0&
#153000
1&
#154000
0&
#155000
b1001 2
b1 /
1&
b1 )
0#
b11 '
#156000
0&
#157000
b1001 1
b1 0
1&
#158000
0&
#159000
1&
#160000
0&
#161000
1&
#162000
0&
#163000
1&
#164000
0&
#165000
b1000 2
b0 /
1&
b0 )
0$
b100 (
b0 '
#166000
0&
#167000
b1000 1
b0 0
1&
#168000
0&
#169000
1&
#170000
0&
#171000
1&
#172000
0&
#173000
1&
#174000
0&
#175000
b1001 2
b10 /
1&
b10 )
1#
b1 '
#176000
0&
#177000
b1001 1
b10 0
1&
#178000
0&
#179000
1&
#180000
0&
#181000
1&
#182000
0&
#183000
1&
#184000
0&
#185000
b1010 2
b11 /
1&
b11 )
1$
b10 '
#186000
0&
#187000
b1010 1
b11 0
1&
#188000
0&
#189000
1&
#190000
0&
#191000
1&
#192000
0&
#193000
1&
#194000
0&
#195000
b1011 2
b1 /
1&
b1 )
0#
b11 '
#196000
0&
#197000
b1011 1
b1 0
1&
#198000
0&
#199000
1&
#200000
0&
#201000
1&
#202000
0&
#203000
1&
#204000
0&
#205000
b1010 2
b0 /
1&
b0 )
0$
b101 (
b0 '
#206000
0&
#207000
b1010 1
b0 0
1&
#208000
0&
#209000
1&
#210000
0&
#211000
1&
#212000
0&
#213000
1&
#214000
0&
#215000
b1011 2
b10 /
1&
b10 )
1#
b1 '
#216000
0&
#217000
b1011 1
b10 0
1&
#218000
0&
#219000
1&
#220000
0&
#221000
1&
#222000
0&
#223000
1&
#224000
0&
#225000
b1100 2
b11 /
1&
b11 )
1$
b10 '
#226000
0&
#227000
b1100 1
b11 0
1&
#228000
0&
#229000
1&
#230000
0&
#231000
1&
#232000
0&
#233000
1&
#234000
0&
#235000
b1101 2
b1 /
1&
b1 )
0#
b11 '
#236000
0&
#237000
b1101 1
b1 0
1&
#238000
0&
#239000
1&
#240000
0&
#241000
1&
#242000
0&
#243000
1&
#244000
0&
#245000
b1100 2
b0 /
1&
b0 )
0$
b110 (
b0 '
#246000
0&
#247000
b1100 1
b0 0
1&
#248000
0&
#249000
1&
#250000
0&
#251000
1&
#252000
0&
#253000
1&
#254000
0&
#255000
b1101 2
b10 /
1&
b10 )
1#
b1 '
#256000
0&
#257000
b1101 1
b10 0
1&
#258000
0&
#259000
1&
#260000
0&
#261000
1&
#262000
0&
#263000
1&
#264000
0&
#265000
b1110 2
b11 /
1&
b11 )
1$
b10 '
#266000
0&
#267000
b1110 1
b11 0
1&
#268000
0&
#269000
1&
#270000
0&
#271000
1&
#272000
0&
#273000
1&
#274000
0&
#275000
b1111 2
b1 /
1&
b1 )
0#
b11 '
#276000
0&
#277000
b1111 1
b1 0
1&
#278000
0&
#279000
1&
#280000
0&
#281000
1&
#282000
0&
#283000
1&
#284000
0&
#285000
b1110 2
b0 /
1&
b0 )
0$
b111 (
b0 '
#286000
0&
#287000
b1110 1
b0 0
1&
#288000
0&
#289000
1&
#290000
0&
#291000
1&
#292000
0&
#293000
1&
#294000
0&
#295000
b1111 2
b10 /
1&
b10 )
1#
b1 '
#296000
0&
#297000
b1111 1
b10 0
1&
#298000
0&
#299000
1&
#300000
0&
#301000
1&
#302000
0&
#303000
1&
#304000
0&
#305000
b10000 2
b11 /
1&
b11 )
1$
b10 '
#306000
0&
#307000
b10000 1
b11 0
1&
#308000
0&
#309000
1&
#310000
0&
#311000
1&
#312000
0&
#313000
1&
#314000
0&
#315000
b10001 2
b1 /
1&
b1 )
0#
b11 '
#316000
0&
#317000
b10001 1
b1 0
1&
#318000
0&
#319000
1&
#320000
0&
#321000
1&
#322000
0&
#323000
1&
#324000
0&
#325000
b10000 2
b0 /
1&
b0 )
0$
b1000 (
b0 '
#326000
0&
#327000
b10000 1
b0 0
1&
#328000
0&
#329000
1&
#330000
0&
#331000
1&
#332000
0&
#333000
1&
#334000
0&
#335000
b10001 2
b10 /
1&
b10 )
1#
b1 '
#336000
0&
#337000
b10001 1
b10 0
1&
#338000
0&
#339000
1&
#340000
0&
#341000
1&
#342000
0&
#343000
1&
#344000
0&
#345000
b10010 2
b11 /
1&
b11 )
1$
b10 '
#346000
0&
#347000
b10010 1
b11 0
1&
#348000
0&
#349000
1&
#350000
0&
#351000
1&
#352000
0&
#353000
1&
#354000
0&
#355000
b10011 2
b1 /
1&
b1 )
0#
b11 '
#356000
0&
#357000
b10011 1
b1 0
1&
#358000
0&
#359000
1&
#360000
0&
#361000
1&
#362000
0&
#363000
1&
#364000
0&
#365000
b10010 2
b0 /
1&
b0 )
0$
b1001 (
b0 '
#366000
0&
#367000
b10010 1
b0 0
1&
#368000
0&
#369000
1&
#370000
0&
#371000
1&
#372000
0&
#373000
1&
#374000
0&
#375000
b10011 2
b10 /
1&
b10 )
1#
b1 '
#376000
0&
#377000
b10011 1
b10 0
1&
#378000
0&
#379000
1&
#380000
0&
#381000
1&
#382000
0&
#383000
1&
#384000
0&
#385000
b10100 2
b11 /
1&
b11 )
1$
b10 '
#386000
0&
#387000
b10100 1
b11 0
1&
#388000
0&
#389000
1&
#390000
0&
#391000
1&
#392000
0&
#393000
1&
#394000
0&
#395000
b10101 2
b1 /
1&
b1 )
0#
b11 '
#396000
0&
#397000
b10101 1
b1 0
1&
#398000
0&
#399000
1&
#400000
0&
#401000
1&
#402000
0&
#403000
1&
#404000
0&
#405000
b10100 2
b0 /
1&
b0 )
0$
b0 (
b0 '
#406000
0&
#407000
b10100 1
b0 0
1&
#408000
0&
#409000
1&
#410000
0&
#411000
1&
#412000
0&
#413000
1&
#414000
0&
#415000
b10011 2
b1 /
1&
b1 )
1$
b1 '
#416000
0&
#417000
b10011 1
b1 0
1&
#418000
0&
#419000
1&
#420000
0&
#421000
1&
#422000
0&
#423000
1&
#424000
0&
#425000
b10100 2
b11 /
1&
b11 )
1#
b10 '
#426000
0&
#427000
b10100 1
b11 0
1&
#428000
0&
#429000
1&
#430000
0&
#431000
1&
#432000
0&
#433000
1&
#434000
0&
#435000
b10011 2
b10 /
1&
b10 )
0$
b11 '
#436000
0&
#437000
b10011 1
b10 0
1&
#438000
0&
#439000
1&
#440000
0&
#441000
1&
#442000
0&
#443000
1&
#444000
0&
#445000
b10010 2
b0 /
1&
b0 )
0#
b1 (
b0 '
#446000
0&
#447000
b10010 1
b0 0
1&
#448000
0&
#449000
1&
#450000
0&
#451000
1&
#452000
0&
#453000
1&
#454000
0&
#455000
b10001 2
b1 /
1&
b1 )
1$
b1 '
#456000
0&
#457000
b10001 1
b1 0
1&
#458000
0&
#459000
1&
#460000
0&
#461000
1&
#462000
0&
#463000
1&
#464000
0&
#465000
b10010 2
b11 /
1&
b11 )
1#
b10 '
#466000
0&
#467000
b10010 1
b11 0
1&
#468000
0&
#469000
1&
#470000
0&
#471000
1&
#472000
0&
#473000
1&
#474000
0&
#475000
b10001 2
b10 /
1&
b10 )
0$
b11 '
#476000
0&
#477000
b10001 1
b10 0
1&
#478000
0&
#479000
1&
#480000
0&
#481000
1&
#482000
0&
#483000
1&
#484000
0&
#485000
b10000 2
b0 /
1&
b0 )
0#
b10 (
b0 '
#486000
0&
#487000
b10000 1
b0 0
1&
#488000
0&
#489000
1&
#490000
0&
#491000
1&
#492000
0&
#493000
1&
#494000
0&
#495000
b1111 2
b1 /
1&
b1 )
1$
b1 '
#496000
0&
#497000
b1111 1
b1 0
1&
#498000
0&
#499000
1&
#500000
0&
#501000
1&
#502000
0&
#503000
1&
#504000
0&
#505000
b10000 2
b11 /
1&
b11 )
1#
b10 '
#506000
0&
#507000
b10000 1
b11 0
1&
#508000
0&
#509000
1&
#510000
0&
#511000
1&
#512000
0&
#513000
1&
#514000
0&
#515000
b1111 2
b10 /
1&
b10 )
0$
b11 '
#516000
0&
#517000
b1111 1
b10 0
1&
#518000
0&
#519000
1&
#520000
0&
#521000
1&
#522000
0&
#523000
1&
#524000
0&
#525000
b1110 2
b0 /
1&
b0 )
0#
b11 (
b0 '
#526000
0&
#527000
b1110 1
b0 0
1&
#528000
0&
#529000
1&
#530000
0&
#531000
1&
#532000
0&
#533000
1&
#534000
0&
#535000
b1101 2
b1 /
1&
b1 )
1$
b1 '
#536000
0&
#537000
b1101 1
b1 0
1&
#538000
0&
#539000
1&
#540000
0&
#541000
1&
#542000
0&
#543000
1&
#544000
0&
#545000
b1110 2
b11 /
1&
b11 )
1#
b10 '
#546000
0&
#547000
b1110 1
b11 0
1&
#548000
0&
#549000
1&
#550000
0&
#551000
1&
#552000
0&
#553000
1&
#554000
0&
#555000
b1101 2
b10 /
1&
b10 )
0$
b11 '
#556000
0&
#557000
b1101 1
b10 0
1&
#558000
0&
#559000
1&
#560000
0&
#561000
1&
#562000
0&
#563000
1&
#564000
0&
#565000
b1100 2
b0 /
1&
b0 )
0#
b100 (
b0 '
#566000
0&
#567000
b1100 1
b0 0
1&
#568000
0&
#569000
1&
#570000
0&
#571000
1&
#572000
0&
#573000
1&
#574000
0&
#575000
b1011 2
b1 /
1&
b1 )
1$
b1 '
#576000
0&
#577000
b1011 1
b1 0
1&
#578000
0&
#579000
1&
#580000
0&
#581000
1&
#582000
0&
#583000
1&
#584000
0&
#585000
b1100 2
b11 /
1&
b11 )
1#
b10 '
#586000
0&
#587000
b1100 1
b11 0
1&
#588000
0&
#589000
1&
#590000
0&
#591000
1&
#592000
0&
#593000
1&
#594000
0&
#595000
b1011 2
b10 /
1&
b10 )
0$
b11 '
#596000
0&
#597000
b1011 1
b10 0
1&
#598000
0&
#599000
1&
#600000
0&
#601000
1&
#602000
0&
#603000
1&
#604000
0&
#605000
1&
b101 (
b100 '
